AUTHORS.rst
CONTRIBUTING.rst
HISTORY.rst
LICENSE
MANIFEST.in
README.rst
setup.cfg
setup.py
ascii_converter/__init__.py
ascii_converter/ascii_converter.py
ascii_converter/cli.py
ascii_converter.egg-info/PKG-INFO
ascii_converter.egg-info/SOURCES.txt
ascii_converter.egg-info/dependency_links.txt
ascii_converter.egg-info/entry_points.txt
ascii_converter.egg-info/not-zip-safe
ascii_converter.egg-info/requires.txt
ascii_converter.egg-info/top_level.txt
docs/Makefile
docs/ascii_converter.rst
docs/authors.rst
docs/conf.py
docs/contributing.rst
docs/history.rst
docs/index.rst
docs/installation.rst
docs/make.bat
docs/modules.rst
docs/readme.rst
docs/usage.rst
docs/_build/html/_static/ajax-loader.gif
docs/_build/html/_static/comment-bright.png
docs/_build/html/_static/comment-close.png
docs/_build/html/_static/comment.png
docs/_build/html/_static/down-pressed.png
docs/_build/html/_static/down.png
docs/_build/html/_static/file.png
docs/_build/html/_static/minus.png
docs/_build/html/_static/plus.png
docs/_build/html/_static/up-pressed.png
docs/_build/html/_static/up.png
tests/test_ascii_converter.py