Metadata-Version: 1.1
Name: ascii-converter
Version: 0.1.0
Summary: AScii-converter utility
Home-page: https://github.com/alejogaci/ascii_converter
Author: Alejandro Garcia Acevedo
Author-email: alejo.garciaa10@gmail.com
License: MIT license
Keywords: ascii_converter
Platform: UNKNOWN
Classifier: Development Status :: 2 - Pre-Alpha
Classifier: Intended Audience :: Developers
Classifier: License :: OSI Approved :: MIT License
Classifier: Natural Language :: English
Classifier: Programming Language :: Python :: 2
Classifier: Programming Language :: Python :: 2.7
Classifier: Programming Language :: Python :: 3
Classifier: Programming Language :: Python :: 3.4
Classifier: Programming Language :: Python :: 3.5
Classifier: Programming Language :: Python :: 3.6
